doxybook/__init__.py
doxybook/__main__.py
doxybook/cache.py
doxybook/constants.py
doxybook/doxygen.py
doxybook/generator.py
doxybook/markdown.py
doxybook/node.py
doxybook/property.py
doxybook/runner.py
doxybook/utils.py
doxybook/xml_parser.py
doxybook/templates/__init__.py
doxybook/templates/annotated.py
doxybook/templates/classes.py
doxybook/templates/files.py
doxybook/templates/hierarchy.py
doxybook/templates/index.py
doxybook/templates/member.py
doxybook/templates/member_definition.py
doxybook/templates/member_table.py
doxybook/templates/modules.py
doxybook/templates/namespaces.py
doxybook/templates/page.py
doxybook/templates/pages.py
doxybook/templates/programlisting.py
doxybook-3.1.4.dist-info/LICENSE
doxybook-3.1.4.dist-info/METADATA
doxybook-3.1.4.dist-info/WHEEL
doxybook-3.1.4.dist-info/entry_points.txt
doxybook-3.1.4.dist-info/top_level.txt
doxybook-3.1.4.dist-info/RECORD
