Metadata-Version: 2.1
Name: doxybook
Version: 3.1.4
Summary: Convert Doxygen XML to GitBook or Vuepress markdown files
Home-page: https://github.com/matusnovak/doxybook
Author: Matus Novak
Author-email: matusnov@gmail.com
License: MIT
Keywords: doxygen gitbook vuepress markdown generator
Platform: UNKNOWN
Requires-Dist: Jinja2
